jsa_data_manager/data_types.py
jsa_data_manager/jsa_data_manager.py
jsa_data_manager/py.typed
jsa_data_manager/warning_and_error.py
jsa_data_manager-0.0.1.dist-info/LICENSE.txt
jsa_data_manager-0.0.1.dist-info/METADATA
jsa_data_manager-0.0.1.dist-info/WHEEL
jsa_data_manager-0.0.1.dist-info/top_level.txt
jsa_data_manager-0.0.1.dist-info/RECORD
