Metadata-Version: 2.1
Name: jsa_data_manager
Version: 0.0.1
Summary: Manages standard input and output data of JSA software tools.
Author-email: Julian Belina <j.belina@fz-juelich.de>
License: MIT License
Classifier: Intended Audience :: Science/Research
Classifier: License :: OSI Approved :: MIT License
Classifier: Natural Language :: English
Classifier: Operating System :: OS Independent
Classifier: Programming Language :: Python
Classifier: Programming Language :: Python :: 3
Classifier: Topic :: Scientific/Engineering :: Mathematics
Classifier: Topic :: Software Development :: Libraries :: Python Modules
Requires-Python: >=3.10
License-File: LICENSE.txt
Requires-Dist: pandas
Requires-Dist: openpyxl
Requires-Dist: netcdf4
Requires-Dist: xarray
Requires-Dist: pydantic
